django_risingwave-0.0.12.dist-info/METADATA
django_risingwave-0.0.12.dist-info/WHEEL
django_risingwave-0.0.12.dist-info/licenses/LICENSE
django_risingwave/__init__.py
django_risingwave/base.py
django_risingwave/client.py
django_risingwave/creation.py
django_risingwave/features.py
django_risingwave/introspection.py
django_risingwave/operations.py
django_risingwave/psycopg_any.py
django_risingwave/schema.py
django_risingwave-0.0.12.dist-info/RECORD
