Metadata-Version: 2.1
Name: django-risingwave
Version: 0.0.12
Summary: A Django ORM connector for RisingWave
Author-Email: Bas Steins <blog@bascodes.com>
Maintainer-Email: Bas Steins <blog@bascodes.com>
License: Copyright (c) Bas Steins.
Classifier: Development Status :: 3 - Alpha
Classifier: Programming Language :: Python :: 3
Classifier: Operating System :: OS Independent
Classifier: Intended Audience :: Developers
Classifier: Framework :: Django
Project-URL: Homepage, https://bas.surf/django-risingwave
Project-URL: Source, https://github.com/bas-codes/django-risingwave
Project-URL: Bug tracker, https://github.com/bas-codes/django-risingwave/issues
Requires-Python: >=3.9
Requires-Dist: django>4.0
